fastoss/__init__.py
fastoss/fastoss.py
fastoss-0.0.8.dist-info/LICENSE
fastoss-0.0.8.dist-info/METADATA
fastoss-0.0.8.dist-info/WHEEL
fastoss-0.0.8.dist-info/top_level.txt
fastoss-0.0.8.dist-info/RECORD
