Metadata-Version: 2.1
Name: fastoss
Version: 0.0.8
Summary: make it easy to use aliyun oss
Home-page: https://gitee.com/ZeroSeeker/fastoss
Author: ZeroSeeker
Author-email: zeroseeker@foxmail.com
Classifier: Programming Language :: Python :: 3
Classifier: License :: OSI Approved :: MIT License
Classifier: Operating System :: OS Independent
License-File: LICENSE
Requires-Dist: oss2 (==2.15.0)
Requires-Dist: envx (>=1.0.1)
Requires-Dist: lazysdk (>=0.1.55)
